{
  "geometricError": 1000.0,
  "root": {
    "children": [
      {
        "geometricError": 0.0,
        "boundingVolume": {
          "region": [
            0.10001707889656244,
            0.7923950208170853,
            0.10042294648746745,
            0.7926965306693221,
            437.3679729067285,
            594.1767285271475
          ]
        },
        "content": {
          "uri": "content/5_18_26.glb"
        }
      },
      {
        "geometricError": 0.0,
        "boundingVolume": {
          "region": [
            0.10042521541549505,
            0.7923961133931972,
            0.10082621528311625,
            0.7927124037055728,
            439.3595866543033,
            663.8965089784035
          ]
        },
        "content": {
          "uri": "content/5_19_26.glb"
        }
      },
      {
        "geometricError": 0.0,
        "boundingVolume": {
          "region": [
            0.1004209376134984,
            0.7927127827282501,
            0.10083080995996355,
            0.7930291094063104,
            434.2815422862456,
            592.9135723270122
          ]
        },
        "content": {
          "uri": "content/5_19_27.glb"
        }
      },
      {
        "geometricError": 0.0,
        "boundingVolume": {
          "region": [
            0.10001661289365216,
            0.7927107438974541,
            0.10022117420863215,
            0.7928683471289092,
            481.04649202484615,
            621.3469772868212
          ]
        },
        "content": {
          "uri": "content/6_36_54.glb"
        }
      },
      {
        "geometricError": 0.0,
        "boundingVolume": {
          "region": [
            0.10004213309797481,
            0.792868288627918,
            0.10022247796958339,
            0.7930219710096699,
            429.66699184409134,
            518.0805979192182
          ]
        },
        "content": {
          "uri": "content/6_36_55.glb"
        }
      },
      {
        "geometricError": 0.0,
        "boundingVolume": {
          "region": [
            0.10022123146509519,
            0.7927605061576511,
            0.10034351355782813,
            0.7928687485405428,
            436.50241051498284,
            510.67183697616565
          ]
        },
        "content": {
          "uri": "content/6_37_54.glb"
        }
      },
      {
        "geometricError": 0.0,
        "boundingVolume": {
          "region": [
            0.10022164021154242,
            0.7928676088546357,
            0.10042680366511435,
            0.7930270324645006,
            428.63628759661486,
            457.5184099577467
          ]
        },
        "content": {
          "uri": "content/6_37_55.glb"
        }
      }
    ],
    "transform": [
      1.0,
      0.0,
      0.0,
      0.0,
      0.0,
      1.0,
      0.0,
      0.0,
      0.0,
      0.0,
      1.0,
      0.0,
      0.0,
      0.0,
      0.0,
      1.0
    ],
    "geometricError": 1000.0,
    "refine": "REPLACE",
    "boundingVolume": {
      "region": [
        0.10001661289365216,
        0.7923950208170853,
        0.10083080995996355,
        0.7930291094063104,
        437.3679729067285,
        594.1767285271475
      ]
    }
  },
  "asset": {
    "generator": "pg2b3dm 2.15.1.0",
    "version": "1.1"
  }
}